setup.py
memcached_lock/__init__.py
memcached_lock.egg-info/PKG-INFO
memcached_lock.egg-info/SOURCES.txt
memcached_lock.egg-info/dependency_links.txt
memcached_lock.egg-info/top_level.txt