Metadata-Version: 1.0
Name: memcached-lock
Version: 1.1
Summary: Implements a distributed lock on top of memcached.
Home-page: http://www.amix.dk/
Author: amix the lucky stiff
Author-email: amix@amix.dk
License: BSD
Keywords: memcached lock distributed
Platform: Any
Classifier: Development Status :: 5 - Production/Stable
Classifier: Intended Audience :: Developers
Classifier: License :: OSI Approved :: BSD License
Classifier: Operating System :: OS Independent
Classifier: Programming Language :: Python
Classifier: Topic :: Software Development :: Libraries :: Python Modules
